nbcelldiff/__init__.py
nbcelldiff/diff_match_patch.py
nbcelldiff/magics.py
nbcelldiff-0.0.1.dist-info/LICENSE
nbcelldiff-0.0.1.dist-info/METADATA
nbcelldiff-0.0.1.dist-info/WHEEL
nbcelldiff-0.0.1.dist-info/top_level.txt
nbcelldiff-0.0.1.dist-info/RECORD
