Metadata-Version: 2.1
Name: nbcelldiff
Version: 0.0.1
Summary: Tools for finding the difference between two notebook code cells
Home-page: https://github.com/innovationOUtside/nb_cell_diff
Author: Tony Hirst
Author-email: tony.hirst@open.ac.uk
License: MIT License
Platform: UNKNOWN
